CHANGELOG.rst
CONTRIBUTING.rst
MANIFEST.in
README.rst
TODO.rst
setup.py
PyChat/__init__.py
PyChat/debugger.py
PyChat/info.py
PyChat/main.py
PyChat.egg-info/PKG-INFO
PyChat.egg-info/SOURCES.txt
PyChat.egg-info/dependency_links.txt
PyChat.egg-info/requires.txt
PyChat.egg-info/top_level.txt
PyChat/client/__init__.py
PyChat/client/connect.py
PyChat/client/error.py
PyChat/client/options.py
PyChat/client/gui/__init__.py
PyChat/client/gui/clientClass.py
PyChat/client/gui/clientGUIClass.py
PyChat/client/gui/connectBoxClass.py
PyChat/client/gui/fileChooserClass.py
PyChat/client/gui/glade/__init__.py
PyChat/client/gui/glade/chatarea.glade
PyChat/client/gui/glade/clientGUI.glade
PyChat/client/gui/glade/connectBox.glade
PyChat/client/gui/glade/filechooser.glade
PyChat/client/gui/glade/tablabel.glade
PyChat/client/gui/helper/__init__.py
PyChat/client/gui/helper/helperFunc.py
PyChat/client/gui/helper/markup.py
PyChat/client/gui/helper/notebook.py
PyChat/client/gui/helper/stack.py
PyChat/client/gui/helper/textview.py
PyChat/client/gui/helper/tests/__init__.py
PyChat/client/gui/helper/tests/test_stack.py
PyChat/client/gui/helper/tests/tests_helperFunc/__init__.py
PyChat/client/gui/helper/tests/tests_helperFunc/test_find_file.py
PyChat/client/gui/helper/tests/tests_helperFunc/test_validate_host.py
PyChat/client/gui/tests/__init__.py
PyChat/client/protocol/ChatClientFactory.py
PyChat/client/protocol/ChatClientProtocol.py
PyChat/client/protocol/FileClientFactory.py
PyChat/client/protocol/FileClientProtocol.py
PyChat/client/protocol/FileSender.py
PyChat/client/protocol/__init__.py
PyChat/client/protocol/tests/__init__.py
PyChat/server/__init__.py
PyChat/server/options.py
PyChat/server/startserver.py
PyChat/server/protocol/__init__.py
PyChat/server/protocol/serverFactory.py
PyChat/server/protocol/serverFtpFactory.py
PyChat/server/protocol/serverFtpProtocol.py
PyChat/server/protocol/serverProtocol.py
bin/pychat
twisted/plugins/server_plugin.py