Metadata-Version: 1.1
Name: PyChat
Version: 1.5.0
Summary: Asynchronous Chat Client
Home-page: http://github.com/leosartaj/PyChat
Author: Sartaj Singh
Author-email: singhsartaj94@gmail.com
License: MIT
Keywords: chat client server
Platform: UNKNOWN
Classifier: Development Status :: 3 - Alpha
Classifier: Topic :: Utilities
Classifier: Topic :: Communications :: Chat
Classifier: License :: OSI Approved :: MIT License
Classifier: Environment :: Plugins
Classifier: Framework :: Twisted
Classifier: Natural Language :: English
Classifier: Programming Language :: Python :: 2.7
